lib_users/__init__.py
lib_users/fd_users.py
lib_users/lib_users.py
lib_users/util/__init__.py
lib_users/util/common.py
lib_users/util/test_common.py
lib_users-0.14.post1.dist-info/entry_points.txt
lib_users-0.14.post1.dist-info/WHEEL
lib_users-0.14.post1.dist-info/METADATA
lib_users-0.14.post1.dist-info/RECORD
