Metadata-Version: 2.1
Name: lib-users
Version: 0.14.post1
Summary: Checks /proc for libraries and files being mapped/open but marked as deleted
Home-page: https://github.com/klausman/lib_users
License: GPL-2.0
Author: Tobias Klausmann
Author-email: klausman@schwarzvogel.de
Requires-Python: >=3.6,<4.0
Classifier: License :: OSI Approved :: GNU General Public License v2 (GPLv2)
Classifier: Programming Language :: Python :: 3
Classifier: Programming Language :: Python :: 3.6
Classifier: Programming Language :: Python :: 3.7
Classifier: Programming Language :: Python :: 3.8
Classifier: Programming Language :: Python :: 3.9
Project-URL: Repository, https://github.com/klausman/lib_users
